MethylVerse/.DS_Store
MethylVerse/__init__.py
MethylVerse/__main__.py
MethylVerse/commandline/__init__.py
MethylVerse/commandline/commands.py
MethylVerse/core/.DS_Store
MethylVerse/core/methyl_core.py
MethylVerse/core/microarray/RawArray.py
MethylVerse/core/microarray/__init__.py
MethylVerse/core/microarray/illumina_normalize.py
MethylVerse/core/microarray/read_IDAT.py
MethylVerse/core/microarray/read_illumina.c
MethylVerse/core/microarray/read_illumina.cpython-312-darwin.so
MethylVerse/core/microarray/read_illumina.pyx
MethylVerse/core/sequencing/__init__.py
MethylVerse/core/sequencing/read_methyldackel/__init__.py
MethylVerse/core/sequencing/read_methyldackel/kseq.h
MethylVerse/core/sequencing/read_methyldackel/process_methyldackel.c
MethylVerse/core/sequencing/read_methyldackel/process_methyldackel.h
MethylVerse/core/sequencing/read_methyldackel/read_methyldackel.c
MethylVerse/core/sequencing/read_methyldackel/read_methyldackel.cpython-312-darwin.so
MethylVerse/core/sequencing/read_methyldackel/read_methyldackel.pxd
MethylVerse/core/sequencing/read_methyldackel/read_methyldackel.pyx
MethylVerse/core/sequencing/seq_utilities.py
MethylVerse/core/sequencing/sequencing_core.py
MethylVerse/core/utilities.py
MethylVerse/data/__init__.py
MethylVerse/data/download_data.py
MethylVerse/data/import_data.py
MethylVerse/plot/__init__.py
MethylVerse/plot/plot_bokeh.py
MethylVerse/plot/plot_plt.py
MethylVerse/recipes/__init__.py
MethylVerse/recipes/recipes.py
MethylVerse/tools/.DS_Store
MethylVerse/tools/__init__.py
MethylVerse/tools/classifiers/Architectures/MultiClassEnsemble.py
MethylVerse/tools/classifiers/MPACT/MPACT_classifier.py
MethylVerse/tools/classifiers/MPACT/MPACT_classifier_torch.py
MethylVerse/tools/classifiers/MPACT/MultiClassEnsemble.py
MethylVerse/tools/classifiers/MPACT/__init__.py
MethylVerse/tools/classifiers/__init__.py
MethylVerse/tools/cnvs/__init__.py
MethylVerse/tools/cnvs/idat_cnv_calling.py
MethylVerse/tools/cnvs/seq_cnv_calling.py
methylverse-1.2.1.dist-info/METADATA
methylverse-1.2.1.dist-info/WHEEL
methylverse-1.2.1.dist-info/licenses/LICENSE.md
methylverse-1.2.1.dist-info/RECORD
