Metadata-Version: 2.4
Name: MethylVerse
Version: 1.2.1
Summary: Python package for methylation data
License: GPL-2.0-or-later
License-File: LICENSE.md
Keywords: WGBS,450k,850k,EPIC,methylation
Author: Kyle S. Smith
Author-email: kyle.smith@stjude.org
Maintainer: Kyle S. Smith
Maintainer-email: kyle.smith@stjude.org
Requires-Python: >=3.10
Classifier: Development Status :: 4 - Beta
Classifier: Environment :: Console
Classifier: Intended Audience :: Developers
Classifier: Intended Audience :: Science/Research
Classifier: License :: OSI Approved :: GNU General Public License v2 or later (GPLv2+)
Classifier: Operating System :: POSIX :: Linux
Classifier: Programming Language :: Cython
Classifier: Programming Language :: Python
Classifier: Programming Language :: Python :: 3
Classifier: Programming Language :: Python :: 3.10
Classifier: Programming Language :: Python :: 3.11
Classifier: Programming Language :: Python :: 3.12
Classifier: Programming Language :: Python :: 3.13
Classifier: Programming Language :: Python :: 3.14
Classifier: Programming Language :: Python :: 3.6
Classifier: Topic :: Scientific/Engineering
Classifier: Topic :: Scientific/Engineering :: Bio-Informatics
Classifier: Topic :: Scientific/Engineering :: Mathematics
Classifier: Topic :: Software Development :: Libraries
Classifier: Topic :: Software Development :: Libraries :: Python Modules
Requires-Dist: ailist (>=2.1.7)
Requires-Dist: bokeh (>=3.1.0,<4.0.0)
Requires-Dist: cython (>=3.0.0,<4.0.0)
Requires-Dist: h5py (>=3.12.1)
Requires-Dist: hmmlearn (>=0.3.3)
Requires-Dist: joblib (>=1.4.2)
Requires-Dist: linear_segment (>=1.2.1,<2.0.0)
Requires-Dist: matplotlib (>=3.7.1,<4.0.0)
Requires-Dist: numpy (>=1.23.5)
Requires-Dist: onnxruntime (>=1.20.0)
Requires-Dist: pandas (>=2.0.0,<3.0.0)
Requires-Dist: pysam (>=0.23.1)
Requires-Dist: scikit-learn (>=1.2.2)
Requires-Dist: scikit-network (>=0.33.0)
Requires-Dist: scipy (>=1.9.1)
Requires-Dist: seaborn (>=0.12.2)
Requires-Dist: statsmodels (>=0.14.0)
Project-URL: Documentation, https://www.biosciencestack.com/static/MethylVerse/docs/index.html
Project-URL: Repository, https://github.com/kylessmith/MethylVerse
